vips_hash/__init__.py
vips_hash/auto.py
vips_hash/main.py
vips_hash/preimage.py
vips_hash/utils.py
vips_hash/backends/__init__.py
vips_hash/backends/auto.py
vips_hash/backends/pycryptodomex.py
vips_hash/backends/pysha3.py
vips_hash-0.2.0.dist-info/LICENSE
vips_hash-0.2.0.dist-info/METADATA
vips_hash-0.2.0.dist-info/WHEEL
vips_hash-0.2.0.dist-info/top_level.txt
vips_hash-0.2.0.dist-info/RECORD
